flytekitplugins_geopandas-1.16.12-py3.14-nspkg.pth
flytekitplugins/geopandas/__init__.py
flytekitplugins/geopandas/gdf_transformers.py
flytekitplugins_geopandas-1.16.12.dist-info/METADATA
flytekitplugins_geopandas-1.16.12.dist-info/WHEEL
flytekitplugins_geopandas-1.16.12.dist-info/entry_points.txt
flytekitplugins_geopandas-1.16.12.dist-info/namespace_packages.txt
flytekitplugins_geopandas-1.16.12.dist-info/top_level.txt
flytekitplugins_geopandas-1.16.12.dist-info/RECORD
